arcgis-2.4.1.3.data/platlib/arcgis/__init__.py
arcgis-2.4.1.3.data/platlib/arcgis/env.py
arcgis-2.4.1.3.data/platlib/arcgis/install.py
arcgis-2.4.1.3.data/platlib/arcgis/_impl/__init__.py
arcgis-2.4.1.3.data/platlib/arcgis/_impl/_geometry_engine.py
arcgis-2.4.1.3.data/platlib/arcgis/_impl/backport.py
arcgis-2.4.1.3.data/platlib/arcgis/_impl/comments.py
arcgis-2.4.1.3.data/platlib/arcgis/_impl/imports.py
arcgis-2.4.1.3.data/platlib/arcgis/_impl/notification.py
arcgis-2.4.1.3.data/platlib/arcgis/_impl/oauth.py
arcgis-2.4.1.3.data/platlib/arcgis/_impl/tools.py
arcgis-2.4.1.3.data/platlib/arcgis/_impl/_async/__init__.py
arcgis-2.4.1.3.data/platlib/arcgis/_impl/_async/jobs.py
arcgis-2.4.1.3.data/platlib/arcgis/_impl/common/__init__.py
arcgis-2.4.1.3.data/platlib/arcgis/_impl/common/_arcgis2geojson.py
arcgis-2.4.1.3.data/platlib/arcgis/_impl/common/_clone.py
arcgis-2.4.1.3.data/platlib/arcgis/_impl/common/_deprecate.py
arcgis-2.4.1.3.data/platlib/arcgis/_impl/common/_filters.py
arcgis-2.4.1.3.data/platlib/arcgis/_impl/common/_isd.py
arcgis-2.4.1.3.data/platlib/arcgis/_impl/common/_mixins.py
arcgis-2.4.1.3.data/platlib/arcgis/_impl/common/_query.py
arcgis-2.4.1.3.data/platlib/arcgis/_impl/common/_spatial.py
arcgis-2.4.1.3.data/platlib/arcgis/_impl/common/_utils.py
arcgis-2.4.1.3.data/platlib/arcgis/_impl/common/_itemdef/__init__.py
arcgis-2.4.1.3.data/platlib/arcgis/_impl/common/_itemdef/_expbuilder.py
arcgis-2.4.1.3.data/platlib/arcgis/_impl/common/_itemdef/_storymaps.py
arcgis-2.4.1.3.data/platlib/arcgis/_impl/common/_itemdef/_ts.py
arcgis-2.4.1.3.data/platlib/arcgis/apps/__init__.py
arcgis-2.4.1.3.data/platlib/arcgis/apps/_url_schemes.py
arcgis-2.4.1.3.data/platlib/arcgis/apps/dashboard/__init__.py
arcgis-2.4.1.3.data/platlib/arcgis/apps/dashboard/dashboard.py
arcgis-2.4.1.3.data/platlib/arcgis/apps/dashboard/_details/__init__.py
arcgis-2.4.1.3.data/platlib/arcgis/apps/dashboard/_details/_details.py
arcgis-2.4.1.3.dist-info/licenses/LICENSE.txt
arcgis-2.4.1.3.dist-info/METADATA
arcgis-2.4.1.3.dist-info/WHEEL
arcgis-2.4.1.3.dist-info/top_level.txt
arcgis-2.4.1.3.dist-info/RECORD
