Metadata-Version: 2.4
Name: arcgis
Version: 2.4.1.3
Summary: ArcGIS API for Python
Home-page: https://developers.arcgis.com/python/
Author: Esri
Author-email: python@esri.com
License: Esri Master License Agreement (MLA) - http://www.esri.com/LEGAL/pdfs/mla_e204_e300/english.pdf
Keywords: gis arcgis geographic spatial spatial-data spatial-data-analysis spatial-analysis data-science maps mapping web-mapping python native-development
Platform: Windows
Platform: Linux
Platform: Solaris
Platform: Mac OS-X
Platform: Unix
Classifier: Development Status :: 5 - Production/Stable
Classifier: Topic :: Scientific/Engineering :: GIS
Classifier: Topic :: Internet :: WWW/HTTP :: Site Management
Classifier: Topic :: Scientific/Engineering :: Information Analysis
Classifier: Topic :: Scientific/Engineering :: Visualization
Classifier: Topic :: Software Development :: Libraries :: Python Modules
Classifier: Intended Audience :: Developers
Classifier: Intended Audience :: Science/Research
Classifier: Operating System :: OS Independent
Classifier: License :: Other/Proprietary License
Classifier: Programming Language :: Python :: 3 :: Only
Classifier: Programming Language :: Python :: 3.10
Classifier: Programming Language :: Python :: 3.11
Classifier: Programming Language :: Python :: 3.12
Requires-Python: >=3.10, <3.13
License-File: LICENSE.txt
Requires-Dist: pillow
Requires-Dist: urllib3<3,>=2.1.0
Requires-Dist: cachetools
Requires-Dist: lxml
Requires-Dist: cryptography
Requires-Dist: pandas<2.3.0,>=2.0.0
Requires-Dist: numpy<2,>=1.21.6
Requires-Dist: matplotlib
Requires-Dist: keyring>=23.3.0
Requires-Dist: pylerc
Requires-Dist: ujson>=3
Requires-Dist: truststore>=0.10.0
Requires-Dist: pywin32>=223; platform_system == "Windows"
Requires-Dist: geomet
Requires-Dist: requests<3,>=2.32.3
Requires-Dist: requests-oauthlib
Requires-Dist: requests_toolbelt
Requires-Dist: pyspnego>=0.8.0
Requires-Dist: dask[dataframe]<2025.1.0,>=2024.12.1
Requires-Dist: matplotlib-inline
Requires-Dist: pyarrow<17,>=16
Requires-Dist: puremagic<2,>=1.15
Requires-Dist: pydantic<3,>=2.8.2
Requires-Dist: networkx<4,>=3.3
Requires-Dist: websocket-client<2.0.0,>=1.2.3
Provides-Extra: gp
Requires-Dist: dill; extra == "gp"
Provides-Extra: gdal
Requires-Dist: gdal<4,>=3.9.2; extra == "gdal"
Provides-Extra: kerberos
Requires-Dist: requests-kerberos; extra == "kerberos"
Requires-Dist: requests-gssapi; extra == "kerberos"
Dynamic: author
Dynamic: author-email
Dynamic: classifier
Dynamic: description
Dynamic: description-content-type
Dynamic: home-page
Dynamic: keywords
Dynamic: license
Dynamic: license-file
Dynamic: platform
Dynamic: provides-extra
Dynamic: requires-dist
Dynamic: requires-python
Dynamic: summary
